not_evil_calculator_spaceylad/__init__.py
not_evil_calculator_spaceylad/spaceylad_calculator.py
not_evil_calculator_spaceylad-0.0.8.dist-info/METADATA
not_evil_calculator_spaceylad-0.0.8.dist-info/WHEEL
not_evil_calculator_spaceylad-0.0.8.dist-info/licenses/LICENSE
not_evil_calculator_spaceylad-0.0.8.dist-info/RECORD
